xurl.py
xurl-0.0.5.dist-info/LICENSE
xurl-0.0.5.dist-info/METADATA
xurl-0.0.5.dist-info/WHEEL
xurl-0.0.5.dist-info/entry_points.txt
xurl-0.0.5.dist-info/top_level.txt
xurl-0.0.5.dist-info/RECORD
